Workbook

Sheet Phase 1 - Basic Calculator
A1: PHASE 1: BASIC PROFIT CALCULATOR
A3: COST INPUTS
A4: Product Cost | B4: 0
A5: Shopify Platform Fee % | B5: 0.025
A6: Payment Processing % + Fixed | B6: 0.029
A7: Payment Processing Fixed Fee | B7: 0.3
A8: Shipping Cost to Customer | B8: 0
A10: REVENUE INPUTS
A11: List Price | B11: 0
A12: Actual Sale Price | B12: 0
A14: CALCULATIONS
A15: Shopify Platform Fee | B15: =B12*B5
A16: Payment Processing Fee | B16: =(B12*B6)+B7
A17: Total Fees & COGS | B17: =B4+B16+B15+B8
A19: PROFIT ANALYSIS
A20: Gross Profit | B20: =B12-B17
A21: Profit Margin % | B21: =IF(B12=0,0,B20/B12)
A22: ROI on Investment | B22: =IF(B4=0,0,B20/B4)
A24: BREAK-EVEN ANALYSIS
A25: Break-Even Price (Fixed Costs) | B25: =B4+B8

Sheet Phase 2 - Cross-Platform
A1: PHASE 2: CROSS-PLATFORM ARBITRAGE CALCULATOR
A3: STOCKX SOURCING
A4: StockX Purchase Price | B4: 0
A5: StockX Seller Fee % | B5: 0.095
A6: Shipping to Resale Location | B6: 0
A8: GOAT SOURCING
A9: GOAT Purchase Price | B9: 0
A10: GOAT Seller Fee % | B10: 0.09
A12: SHOPIFY RESALE
A13: Shopify Sale Price | B13: 0
A14: Shopify Platform Fee % | B14: 0.025
A15: Payment Processing % + Fixed | B15: 0.029
A16: Payment Processing Fixed | B16: 0.3
A17: Shopify Fulfillment Cost | B17: 0
A19: SPREAD ANALYSIS
A20: Price Spread (StockX vs Shopify) | B20: =B13-B4
A21: Spread % (Opportunity Size) | B21: =IF(B4=0,0,B20/B4)
A22: Minimum Spread Threshold | B22: 100
A23: Qualifies for Arbitrage? | B23: =IF(B20>=B22,"YES","NO")
A25: NET PROFIT ANALYSIS
A26: Total Cost of Goods | B26: =B4+(B4*B5)+B6
A27: Shopify Fees | B27: =(B13*B14)+((B13*B15)+B16)
A28: Total Fulfillment Costs | B28: =B17+B6
A29: Net Profit (All Fees) | B29: =B13-B26-B27-B28
A30: Profit Margin % | B30: =IF(B13=0,0,B29/B13)

Sheet Phase 3 - Pokémon TCG
A1: PHASE 3: POKÉMON TCG SEALED PRODUCT CALCULATOR
A3: SOURCING COSTS
A4: Sealed Product Purchase Price | B4: 0
A5: Source Fee % (if applicable) | B5: 0.05
A6: Shipping to Grading Service | B6: 0
A8: GRADING SERVICE FEES
A9: PSA Grading Fee | B9: 79.99
A10: CGC Grading Fee | B10: 15
A11: BGS Grading Fee | B11: 35
A12: Selected Grading Service Fee | B12: 0
A13: Return Shipping from Grader | B13: 0
A15: RESALE ASSUMPTIONS
A16: Estimated StockX/eBay Resale Price | B16: 0
A17: StockX/eBay Fee % | B17: 0.105
A18: Shipping to Buyer | B18: 0
A19: Holding Period (Days) | B19: 30
A20: Storage Cost (Monthly) | B20: 0
A22: PROFIT ANALYSIS
A23: Total Acquisition Cost | B23: =B4+(B4*B5)+B6
A24: Total Grading Cost | B24: =B12+B13
A25: Holding Period Cost | B25: =(B19/30)*B20
A26: Total Investment | B26: =B23+B24+B25
A28: Resale Marketplace Fee | B28: =B16*B17
A29: Net Resale Proceeds | B29: =B16-B28-B18
A31: NET PROFIT | B31: =B29-B26
A32: Profit Margin % | B32: =IF(B16=0,0,B31/B16)
A33: ROI on Total Investment | B33: =IF(B26=0,0,B31/B26)
A34: Annualized ROI (365 days) | B34: =IF(B19=0,0,B33*(365/B19))

Sheet Scenario Analysis
A1: SCENARIO ANALYSIS - 12 MONTH PROJECTION
A3: CONSERVATIVE CASE
A4: Assumed Profit Margin | B4: 0.5
A5: Average Profit per Deal | B5: 0
A6: Deals per Day | B6: 2
A7: Working Days per Month | B7: 22
A8: Monthly Profit | B8: =B5*B6*B7
A9: Quarterly Profit | B9: =B8*3
A10: Annual Profit | B10: =B8*12
A12: REALISTIC CASE
A13: Assumed Profit Margin | C13: 0.65
A14: Average Profit per Deal | C14: 0
A15: Deals per Day | C15: 3
A16: Working Days per Month | C16: 22
A17: Monthly Profit | C17: =C14*C15*C16
A18: Quarterly Profit | C18: =C17*3
A19: Annual Profit | C19: =C17*12
A21: AGGRESSIVE CASE
A22: Assumed Profit Margin | D22: 0.75
A23: Average Profit per Deal | D23: 0
A24: Deals per Day | D24: 5
A25: Working Days per Month | D25: 22
A26: Monthly Profit | D26: =D23*D24*D25
A27: Quarterly Profit | D27: =D26*3
A28: Annual Profit | D28: =D26*12

Sheet Break-Even Analysis
A1: BREAK-EVEN & ROI ANALYSIS
A3: DAILY BREAK-EVEN ANALYSIS
A4: Target Hourly Rate ($/hr) | B4: 50
A5: Working Hours per Day | B5: 8
A6: Daily Income Target | B6: =B4*B5
A7: Average Profit per Deal | B7: 0
A8: Deals Required per Day | B8: =IF(B7=0,0,B6/B7)
A10: AUTOMATION/SUBSCRIPTION ROI
A11: Monthly Automation Cost (Zapier, Make, etc.) | B11: 0
A12: Initial Automation Setup Cost | B12: 0
A13: Time Saved per Deal (minutes) | B13: 0
A14: Deals per Month | B14: 0
A15: Total Minutes Saved per Month | B15: =B13*B14
A16: Hours Saved per Month | B16: =B15/60
A17: Value of Time Saved (at $50/hr) | B17: =B16*50
A18: Monthly Net Benefit | B18: =B17-B11
A19: Payback Period (Months) | B19: =IF(B18=0,"N/A",IF(B18>0,B12/B18,"N/A"))
A21: CAPITAL INVESTMENT BREAK-EVEN
A22: Initial Capital Required | B22: 0
A23: Average Monthly Profit | B23: 0
A24: Months to Break-Even | B24: =IF(B23=0,"N/A",B22/B23)
A25: Annual Profit at Break-Even | B25: =B23*12

Sheet 12-Month Projection
A1: 12-MONTH PROFIT PROJECTION
A3: Month | B3: Conservative Case | C3: Realistic Case | D3: Aggressive Case | E3: Average Projection
A4: January | B4: ='Scenario Analysis'!$B$8 | C4: ='Scenario Analysis'!$C$17 | D4: ='Scenario Analysis'!$D$26 | E4: =(B4+C4+D4)/3
A5: February | B5: ='Scenario Analysis'!$B$8 | C5: ='Scenario Analysis'!$C$17 | D5: ='Scenario Analysis'!$D$26 | E5: =(B5+C5+D5)/3
A6: March | B6: ='Scenario Analysis'!$B$8 | C6: ='Scenario Analysis'!$C$17 | D6: ='Scenario Analysis'!$D$26 | E6: =(B6+C6+D6)/3
A7: April | B7: ='Scenario Analysis'!$B$8 | C7: ='Scenario Analysis'!$C$17 | D7: ='Scenario Analysis'!$D$26 | E7: =(B7+C7+D7)/3
A8: May | B8: ='Scenario Analysis'!$B$8 | C8: ='Scenario Analysis'!$C$17 | D8: ='Scenario Analysis'!$D$26 | E8: =(B8+C8+D8)/3
A9: June | B9: ='Scenario Analysis'!$B$8 | C9: ='Scenario Analysis'!$C$17 | D9: ='Scenario Analysis'!$D$26 | E9: =(B9+C9+D9)/3
A10: July | B10: ='Scenario Analysis'!$B$8 | C10: ='Scenario Analysis'!$C$17 | D10: ='Scenario Analysis'!$D$26 | E10: =(B10+C10+D10)/3
A11: August | B11: ='Scenario Analysis'!$B$8 | C11: ='Scenario Analysis'!$C$17 | D11: ='Scenario Analysis'!$D$26 | E11: =(B11+C11+D11)/3
A12: September | B12: ='Scenario Analysis'!$B$8 | C12: ='Scenario Analysis'!$C$17 | D12: ='Scenario Analysis'!$D$26 | E12: =(B12+C12+D12)/3
A13: October | B13: ='Scenario Analysis'!$B$8 | C13: ='Scenario Analysis'!$C$17 | D13: ='Scenario Analysis'!$D$26 | E13: =(B13+C13+D13)/3
A14: November | B14: ='Scenario Analysis'!$B$8 | C14: ='Scenario Analysis'!$C$17 | D14: ='Scenario Analysis'!$D$26 | E14: =(B14+C14+D14)/3
A15: December | B15: ='Scenario Analysis'!$B$8 | C15: ='Scenario Analysis'!$C$17 | D15: ='Scenario Analysis'!$D$26 | E15: =(B15+C15+D15)/3
A17: CUMULATIVE TOTALS
A18: 6-Month Total | B18: =SUM(B4:B9) | C18: =SUM(C4:C9) | D18: =SUM(D4:D9) | E18: =SUM(E4:E9)
A19: 12-Month Total | B19: =SUM(B4:B15) | C19: =SUM(C4:C15) | D19: =SUM(D4:D15) | E19: =SUM(E4:E15)
